README.rst
setup.py
pyorphans/__about__.py
pyorphans/__init__.py
pyorphans/cli.py
pyorphans/utils.py
pyorphans.egg-info/PKG-INFO
pyorphans.egg-info/SOURCES.txt
pyorphans.egg-info/dependency_links.txt
pyorphans.egg-info/entry_points.txt
pyorphans.egg-info/top_level.txt