Metadata-Version: 1.1
Name: pyorphans
Version: 0.2.2
Summary: Find dirs which appear to be broken python packages, as a pre-commit hook.
Home-page: https://github.com/depop/pyorphans
Author: Depop
Author-email: dev@depop.com
License: Apache 2.0
Platform: UNKNOWN
Classifier: Intended Audience :: Developers
Classifier: License :: OSI Approved :: Apache Software License
Classifier: Operating System :: OS Independent
Classifier: Programming Language :: Python
Classifier: Programming Language :: Python :: 3
Classifier: Programming Language :: Python :: 2.7
